slovik/__init__.py
slovik-1.0.dist-info/METADATA
slovik-1.0.dist-info/WHEEL
slovik-1.0.dist-info/top_level.txt
slovik-1.0.dist-info/RECORD
