Metadata-Version: 2.1
Name: slovik
Version: 1.0
Summary: EZ
Home-page: UNKNOWN
Author: Chelik
Author-email: kto9228322@gmail.com
License: UNKNOWN
Platform: UNKNOWN
Classifier: Programming Language :: Python :: 3
Classifier: License :: OSI Approved :: MIT License
Classifier: Operating System :: OS Independent
Requires-Python: >=3.6
